asie_api/__init__.py
asie_api/client.py
data_api/__init__.py
data_api/client.py
asie_api-0.0.2.dist-info/METADATA
asie_api-0.0.2.dist-info/WHEEL
asie_api-0.0.2.dist-info/top_level.txt
asie_api-0.0.2.dist-info/RECORD
